{
  "ComponentIndexes": {},
  "ControlUniqueIds": {
    "App": 1,
    "Label1": 5,
    "Label2": 7,
    "Label3": 4,
    "Label4": 6,
    "Screen1": 3
  },
  "FunctionParamsInvariantScripts": {},
  "FunctionParamsInvariantScriptsOnInstances": {},
  "HeaderLastSavedDateTimeUTC": "07/05/2022 18:11:46",
  "IsLegacyComponentAllowGlobalScopeCase": false,
  "LocalConnectionIDReferences": {},
  "LocalDatabaseReferencesAsEmpty": false,
  "LocalResourceFileNames": {},
  "LocalResourceRootPaths": {},
  "OrderComponentMetadata": {},
  "OrderComponentTemplate": {},
  "OrderDataSource": {},
  "OrderGroupControls": {},
  "OrderPcfTemplate": {},
  "OrderTemplate": {},
  "OrderXMLTemplate": {
    "label": 0
  },
  "PublishOrderIndices": {
    "App": 0,
    "Label1": 4,
    "Label2": 6,
    "Label3": 3,
    "Label4": 5,
    "Screen1": 2
  },
  "ResourcesJsonIndices": {},
  "RuleScreenIdWithoutScreen": {},
  "TemplateVersions": {},
  "VolatileProperties": {
    "AnalysisLoadTime": 0.019818,
    "ControlCount": {
      "label": 4,
      "screen": 1
    },
    "DeserializationLoadTime": 0.8029335,
    "ErrorCount": 0
  },
  "WasLocalDatabaseReferencesEmpty": true
}